<?xml version="1.0" standalone="no"?>

<upgrade>
	
	<image path="../../icons/book_of_secrets.png" />
	<image-cancel path="../../units/merlin/images/magic_cancel.bmp" />
	<time value="300"/>

	<unit-requirements>
		<unit name="merlin" />
	</unit-requirements>
	<upgrade-requirements/>
	<resource-requirements>
		<resource name="wood" amount="200"/>
		<resource name="stone" amount="200" />
		<resource name="gold" amount="500"/>
	</resource-requirements>
	
	<enhancements>
		
		<enhancement>
			<affects>
				<unit name="merlin"/>
			</affects>
			<effects>
				<static-modifiers>
					<max-ep value="1500" />
					<ep-regeneration value="5" />
				</static-modifiers>
			</effects>			
		</enhancement>
		
	</enhancements>
	
</upgrade>