<?xml version="1.0" standalone="no"?>
<unit>
  <parameters>
    <armor-type value="void"/>
    <time value="25"/>
    <multi-selection value="true"/>
    <fields>
      <field value="land"/>
    </fields>
    <properties/>
    <meeting-point value="false"/>
    <cellmap value="false"/>
  </parameters>
  <item-limit limit="60"/>
  <creatable-type>
    <size value="1"/>
    <height value="2"/>
    <stats>
      <max-hp value="50" regeneration="0"/>
      <max-ep value="0" regeneration="0"/>
      <max-sp value="0" regeneration="0"/>
      <max-cp value="-1" />
      <sight value="10"/>
      <armor value="0"/>
    </stats>
    <producible>
      <time value="10"/>
      <properties/>
      <light enabled="false"/>
      <unit-requirements/>
      <upgrade-requirements/>
        <resource-requirements>
          <resource name="wealth" amount="200" plus="0" multiply="0"/>
        </resource-requirements>
      <image path="images/archer.bmp"/>
      <image-cancel path="../ranger/images/tech_cancel.bmp"/>
      </producible>
    <resource-production>
      <resources-stored>
        <resource name="wealth" amount="100000"/>
      </resources-stored>
    </resource-production>
    <actions>
      <skills>
		<skill>
			<type value="stop"/>
			<name value="stop_skill"/>		
			<ep-cost value="0"/>
			<speed value="1000"/>
			<anim-speed value="45"/>
			<animation path="models/archer_stand.g3d"/>
			<sound enabled="false"/>
		</skill>
		<skill>
			<type value="move"/>
			<name value="move_skill"/>		
			<ep-cost value="0"/>
			<speed value="240"/>
			<anim-speed value="130"/>
			<animation path="models/archer_walk.g3d"/>
			<sound enabled="false"/>
		</skill>
		<skill>
			<type value="attack"/>
			<name value="attack_skill"/>		
			<ep-cost value="0"/>
			<speed value="55"/>
			<anim-speed value="55"/>
			<animation path="models/archer_attack.g3d"/>
			<sound enabled="false"/>
			<attack-strenght value="0"/>
			<attack-var value="0"/>
			<attack-range value="9"/>
			<attack-type value="piercing"/>
			<attack-start-time value="0.35"/>
			<attack-fields>
				<field value="land"/>
				<field value="air"/>
			</attack-fields>
			<projectile value="true">
			<particle value="true" path="particle_proj.xml"/>
			<sound enabled="false"/>
			</projectile>
			<splash value="false"/>
            		<damage-types>
                		<damage-type type="piercing" value="10"/>
            		</damage-types>
		</skill>
		<skill>
			<type value="die"/>
			<name value="die_skill"/>		
			<ep-cost value="0"/>
			<speed value="60"/>
			<anim-speed value="60"/>
			<animation path="models/archer_die.g3d"/>
			<sound enabled="false"/>			
			<fade value="false"/>
		</skill>
      </skills>
      <commands>
		<command>
			<type value="stop"/>
			<name value="stop"/>
			<image path="images/tech_stop.bmp"/>
			<unit-requirements/>
			<upgrade-requirements/>
			<stop-skill value="stop_skill"/>
		</command>
		<command>
			<type value="move"/>
			<name value="move"/>
			<image path="images/tech_move.bmp"/>
			<unit-requirements/>
			<upgrade-requirements/>
			<move-skill value="move_skill"/>
		</command>
		<command>
			<type value="attack"/>
			<name value="attack"/>
			<image path="images/archer_attack.bmp"/>
			<unit-requirements/>
			<upgrade-requirements/>
			<move-skill value="move_skill"/>
			<attack-skill value="attack_skill"/>
		</command>
      </commands>
    </actions>
  </creatable-type>
	<selection-sounds enabled="true">
		<sound path="sounds/archer_select1.wav"/>
		<sound path="sounds/archer_select2.wav"/>
		<sound path="sounds/archer_select3.wav"/>
		<sound path="sounds/archer_select4.wav"/>
		<sound path="sounds/archer_select5.wav"/>
		<sound path="sounds/archer_select6.wav"/>
		<sound path="sounds/archer_select7.wav"/>
		<sound path="sounds/archer_select8.wav"/>
		<sound path="sounds/archer_select9.wav"/>
		<sound path="sounds/archer_select10.wav"/>
		<sound path="sounds/archer_select11.wav"/>
	</selection-sounds>
	<command-sounds enabled="true">
		<sound path="sounds/archer_ack1.wav"/>
		<sound path="sounds/archer_ack2.wav"/>
		<sound path="sounds/archer_ack3.wav"/>
		<sound path="sounds/archer_ack4.wav"/>
		<sound path="sounds/archer_ack5.wav"/>
		<sound path="sounds/archer_ack6.wav"/>
		<sound path="sounds/archer_ack7.wav"/>
		<sound path="sounds/archer_ack8.wav"/>
		<sound path="sounds/archer_ack9.wav"/>
		<sound path="sounds/archer_ack10.wav"/>
		<sound path="sounds/archer_ack11.wav"/>
		<sound path="sounds/archer_ack12.wav"/>
		<sound path="sounds/archer_ack13.wav"/>
		<sound path="sounds/archer_ack14.wav"/>
		<sound path="sounds/archer_ack15.wav"/>
	</command-sounds>
</unit>